[{"id":83,"campsiteId":-1,"startDate":1667620800000,"endDate":1667707200000,"username":"Ligma","paid":false,"price":0.0},{"id":84,"campsiteId":-1,"startDate":1667707200000,"endDate":1667883600000,"username":"1","paid":false,"price":0.0},{"id":86,"campsiteId":-1,"startDate":1668488400000,"endDate":1668747600000,"username":"1","paid":false,"price":0.0},{"id":87,"campsiteId":-1,"startDate":1669093200000,"endDate":1669266000000,"username":"1","paid":false,"price":0.0},{"id":104,"campsiteId":-1,"startDate":1669784400000,"endDate":1670475600000,"username":"spider","paid":false,"price":0.0}]